{
  "date": "2026-06-26",
  "candidates": [
    {
      "code": "688012",
      "name": "中微公司",
      "sector": "半导体",
      "score": 7,
      "rank_in_sector": 1,
      "label": "candidate",
      "return": 3.48,
      "volume_ratio": 1.08,
      "relative_strength": 2
    },
    {
      "code": "000725",
      "name": "京东方Ａ",
      "sector": "光学光电子",
      "score": 7,
      "rank_in_sector": 1,
      "label": "candidate",
      "return": 3.59,
      "volume_ratio": 1.27,
      "relative_strength": 2
    },
    {
      "code": "002714",
      "name": "牧原股份",
      "sector": "农牧饲渔",
      "score": 7,
      "rank_in_sector": 1,
      "label": "candidate",
      "return": 3.71,
      "volume_ratio": 1.98,
      "relative_strength": 1
    },
    {
      "code": "300498",
      "name": "温氏股份",
      "sector": "农牧饲渔",
      "score": 7,
      "rank_in_sector": 2,
      "label": "candidate",
      "return": 3.75,
      "volume_ratio": 2.03,
      "relative_strength": 1
    }
  ],
  "top_sectors": [
    {
      "name": "玻璃玻纤",
      "code": "BK0546",
      "change_pct": 1.62,
      "trend": 2,
      "momentum": 1,
      "money_flow": 1,
      "breadth": 1,
      "stability": 1,
      "score": 6,
      "label": "rotation",
      "rank": 1
    },
    {
      "name": "光学光电子",
      "code": "BK1038",
      "change_pct": 0.35,
      "trend": 1,
      "momentum": 1,
      "money_flow": 0,
      "breadth": 1,
      "stability": 1,
      "score": 4,
      "label": "watch",
      "rank": 2
    },
    {
      "name": "电子化学品Ⅱ",
      "code": "BK1039",
      "change_pct": 0.36,
      "trend": 1,
      "momentum": 1,
      "money_flow": 0,
      "breadth": 1,
      "stability": 1,
      "score": 4,
      "label": "watch",
      "rank": 3
    },
    {
      "name": "教育",
      "code": "BK0740",
      "change_pct": 0.77,
      "trend": 1,
      "momentum": 1,
      "money_flow": 0,
      "breadth": 0,
      "stability": 1,
      "score": 3,
      "label": "filter",
      "rank": 4
    },
    {
      "name": "航空机场",
      "code": "BK0420",
      "change_pct": -2.3,
      "trend": 0,
      "momentum": 0,
      "money_flow": 0,
      "breadth": 0,
      "stability": 1,
      "score": 1,
      "label": "filter",
      "rank": 5
    },
    {
      "name": "铁路公路",
      "code": "BK0421",
      "change_pct": -1.57,
      "trend": 0,
      "momentum": 0,
      "money_flow": 0,
      "breadth": 0,
      "stability": 1,
      "score": 1,
      "label": "filter",
      "rank": 6
    },
    {
      "name": "物流",
      "code": "BK0422",
      "change_pct": -1.49,
      "trend": 0,
      "momentum": 0,
      "money_flow": 0,
      "breadth": 0,
      "stability": 1,
      "score": 1,
      "label": "filter",
      "rank": 7
    },
    {
      "name": "水泥",
      "code": "BK0424",
      "change_pct": -2.06,
      "trend": 0,
      "momentum": 0,
      "money_flow": 0,
      "breadth": 0,
      "stability": 1,
      "score": 1,
      "label": "filter",
      "rank": 8
    },
    {
      "name": "公用事业",
      "code": "BK0427",
      "change_pct": -1.71,
      "trend": 0,
      "momentum": 0,
      "money_flow": 0,
      "breadth": 0,
      "stability": 1,
      "score": 1,
      "label": "filter",
      "rank": 9
    },
    {
      "name": "电力",
      "code": "BK0428",
      "change_pct": -1.42,
      "trend": 0,
      "momentum": 0,
      "money_flow": 0,
      "breadth": 0,
      "stability": 1,
      "score": 1,
      "label": "filter",
      "rank": 10
    },
    {
      "name": "农林牧渔",
      "code": "BK0433",
      "change_pct": -1.34,
      "trend": 0,
      "momentum": 0,
      "money_flow": 0,
      "breadth": 0,
      "stability": 1,
      "score": 1,
      "label": "filter",
      "rank": 11
    },
    {
      "name": "纺织服饰",
      "code": "BK0436",
      "change_pct": -1.93,
      "trend": 0,
      "momentum": 0,
      "money_flow": 0,
      "breadth": 0,
      "stability": 1,
      "score": 1,
      "label": "filter",
      "rank": 12
    },
    {
      "name": "煤炭",
      "code": "BK0437",
      "change_pct": -3.12,
      "trend": 0,
      "momentum": 0,
      "money_flow": 0,
      "breadth": 0,
      "stability": 1,
      "score": 1,
      "label": "filter",
      "rank": 13
    },
    {
      "name": "食品饮料",
      "code": "BK0438",
      "change_pct": -2.22,
      "trend": 0,
      "momentum": 0,
      "money_flow": 0,
      "breadth": 0,
      "stability": 1,
      "score": 1,
      "label": "filter",
      "rank": 14
    },
    {
      "name": "家居用品",
      "code": "BK0440",
      "change_pct": -1.69,
      "trend": 0,
      "momentum": 0,
      "money_flow": 0,
      "breadth": 0,
      "stability": 1,
      "score": 1,
      "label": "filter",
      "rank": 15
    },
    {
      "name": "通信设备",
      "code": "BK0448",
      "change_pct": -5.0,
      "trend": 0,
      "momentum": 0,
      "money_flow": 0,
      "breadth": 0,
      "stability": 1,
      "score": 1,
      "label": "filter",
      "rank": 16
    },
    {
      "name": "航运港口",
      "code": "BK0450",
      "change_pct": -2.5,
      "trend": 0,
      "momentum": 0,
      "money_flow": 0,
      "breadth": 0,
      "stability": 1,
      "score": 1,
      "label": "filter",
      "rank": 17
    },
    {
      "name": "房地产开发",
      "code": "BK0451",
      "change_pct": -1.44,
      "trend": 0,
      "momentum": 0,
      "money_flow": 0,
      "breadth": 0,
      "stability": 1,
      "score": 1,
      "label": "filter",
      "rank": 18
    },
    {
      "name": "塑料",
      "code": "BK0454",
      "change_pct": -2.88,
      "trend": 0,
      "momentum": 0,
      "money_flow": 0,
      "breadth": 0,
      "stability": 1,
      "score": 1,
      "label": "filter",
      "rank": 19
    },
    {
      "name": "家用电器",
      "code": "BK0456",
      "change_pct": -2.55,
      "trend": 0,
      "momentum": 0,
      "money_flow": 0,
      "breadth": 0,
      "stability": 1,
      "score": 1,
      "label": "filter",
      "rank": 20
    }
  ]
}